{
 "joueurs": [
  {
   "surname": "Albert",
   "firstname": "Alice",
   "birthday": "0"
  },
  {
   "surname": "Beatrice",
   "firstname": "Alice",
   "birthday": "0"
  },
  {
   "surname": "Carole",
   "firstname": "Alice",
   "birthday": "0"
  },
  {
   "surname": "Denis",
   "firstname": "Alice",
   "birthday": "0"
  },
  {
   "surname": "Edouard",
   "firstname": "Alice",
   "birthday": "0"
  },
  {
   "surname": "Francois",
   "firstname": "Alice",
   "birthday": "0"
  },
  {
   "surname": "Gérard",
   "firstname": "Alice",
   "birthday": "0"
  },
  {
   "surname": "Hector",
   "firstname": "Alice",
   "birthday": "0"
  },
  {
   "surname": "Isabelle",
   "firstname": "Alice",
   "birthday": "0"
  },
  {
   "surname": "Jules",
   "firstname": "Alice",
   "birthday": "0"
  },
  {
   "surname": "Karl",
   "firstname": "Alice",
   "birthday": "0"
  },
  {
   "surname": "Louis",
   "firstname": "Alice",
   "birthday": "0"
  }
]
}